README
setup.py
simpletransfers/__init__.py
simpletransfers/ftp.py
simpletransfers/http_client.py
simpletransfers/http_server.py
simpletransfers/local.py
simpletransfers/mail.py
simpletransfers/sftp.py
simpletransfers/soap.py
simpletransfers/zip.py
simpletransfers.egg-info/PKG-INFO
simpletransfers.egg-info/SOURCES.txt
simpletransfers.egg-info/dependency_links.txt
simpletransfers.egg-info/top_level.txt
simpletransfers/tests/__init__.py
simpletransfers/tests/one.txt
simpletransfers/tests/test.zip
simpletransfers/tests/testftp.py
simpletransfers/tests/testhttpclient.py
simpletransfers/tests/testhttpserver.py
simpletransfers/tests/testlocal.py
simpletransfers/tests/testmail.py
simpletransfers/tests/testsftp.py
simpletransfers/tests/testsoap.py
simpletransfers/tests/testzip.py