Metadata-Version: 1.1
Name: simpletransfers
Version: 1.3.1
Summary: Simple file transfer library
Home-page: https://bitbucket.org/jestersghost/simpletransfers
Author: Jesters Ghost
Author-email: jestersghost@gmail.com
License: UNKNOWN
Platform: UNKNOWN
Requires: ctxlogger
